incantoos/__init__.py
incantoos-1.1.0.dist-info/licenses/LICENSE
incantoos-1.1.0.dist-info/METADATA
incantoos-1.1.0.dist-info/WHEEL
incantoos-1.1.0.dist-info/top_level.txt
incantoos-1.1.0.dist-info/RECORD
