Metadata-Version: 2.4
Name: incantoos
Version: 1.1.0
Summary: IncantoOS Is a wrapper related to OS functions that can be put into a smaller faster function
Home-page: https://github.com/NinoTheMeano/incantoos
Author: NinoTheMeano
Author-email: ninosdeveloping@gmail.com
Project-URL: Discord, https://discord.com/users/255125932447236096
Classifier: Programming Language :: Python :: 3
Classifier: License :: OSI Approved :: MIT License
Classifier: Operating System :: OS Independent
Classifier: Framework :: AsyncIO
Classifier: Topic :: Internet :: WWW/HTTP :: Dynamic Content :: CGI Tools/Libraries
Classifier: Topic :: Software Development :: Libraries
Requires-Python: >=3.8
License-File: LICENSE
Dynamic: author
Dynamic: author-email
Dynamic: classifier
Dynamic: description
Dynamic: description-content-type
Dynamic: home-page
Dynamic: license-file
Dynamic: project-url
Dynamic: requires-python
Dynamic: summary
